vacheck/__init__.py
vacheck/datacheck5.py
vacheck/exceptions.py
vacheck/data/example_input.csv
vacheck/data/probbaseV5.csv
vacheck-0.0.3.dist-info/LICENSE
vacheck-0.0.3.dist-info/METADATA
vacheck-0.0.3.dist-info/WHEEL
vacheck-0.0.3.dist-info/top_level.txt
vacheck-0.0.3.dist-info/RECORD
