Metadata-Version: 2.1
Name: vacheck
Version: 0.0.3
Summary: Verbal autopsy data consistency checks (from InterVA algorithm).
Author-email: Jason Thomas <jarathomas@gmail.com>
Maintainer-email: Jason Thomas <jarathomas@gmail.com>
License: GPLv3
Project-URL: Homepage, https://github.com/verbal-autopsy-software/vacheck
Project-URL: Bug Tracker, https://github.com/verbal-autopsy-software/vacheck/issues
Keywords: verbal autopsy
Classifier: Programming Language :: Python :: 3
Classifier: Programming Language :: Python :: 3.8
Classifier: Programming Language :: Python :: 3.9
Classifier: Programming Language :: Python :: 3.10
Classifier: Programming Language :: Python :: 3.11
Classifier: Programming Language :: Python :: 3.12
Classifier: License :: OSI Approved :: GNU General Public License v3 (GPLv3)
Classifier: Operating System :: OS Independent
Requires-Python: >=3.8
License-File: LICENSE
Requires-Dist: pandas
Requires-Dist: numpy
